Workbook
Name NativeTimeline_Hiring_Date: #N/A
Name Slicer_Country: #N/A
Name Slicer_Department: #N/A
Name Slicer_Work_Type: #N/A
Name t: INDEX(([1]Lookup!XEX24:XEX1048570,[1]Lookup!XEW24:XEW1048570,[1]Lookup!XEY24:XEY1048570),,,2)

Sheet Basic
A1: ID | B1: First Name | C1: Last Name | D1: Full Name | E1: Gender | F1: Phone | G1: Country | H1: Work Type | I1: Department | J1: MonyTransfere | K1: Email | L1: Hire Day | M1: Hire Month | N1: Hire Year | O1: Hiring Date | P1: current date | Q1: Experience Year | R1: Salary | S1: Tax 10% | T1: Bonus 3% | U1: Net Salary | V1: Salary Status | W1: Extra Bonus | Y1: = | Z1: Net >=6000 (Over) | AA1: Net <6000 (Normal)
A2: 1001 | B2: Ghadir | C2: AhmeD | D2: =PROPER(TRIM(FatmaUsf[[#This Row],[Last Name]]&" "&FatmaUsf[[#This Row],[Last Name]])) -> Ahmed Ahmed | E2: Female | F2: 012 2910-2426 | G2: Sudan | H2: Full Time | I2: Manufacturing | J2: Debt Card | K2: g.ahmed@email.com | L2: 5 | M2: 4 | N2: 2023 | O2: =DATE(FatmaUsf[[#This Row],[Hire Year]],FatmaUsf[[#This Row],[Hire Month]],FatmaUsf[[#This Row],[Hire Day]]) -> 45021 | P2: =TODAY() -> 46071 | Q2: =DATEDIF(FatmaUsf[[#This Row],[Hiring Date]],FatmaUsf[[#This Row],[current date]],"Y") -> 2 | R2: 6548 | S2: =FatmaUsf[[#This Row],[Salary]]*0.1 -> 654.8 | T2: =FatmaUsf[[#This Row],[Salary]]*0.03 -> 196.44 | U2: =FatmaUsf[[#This Row],[Salary]]-FatmaUsf[[#This Row],[Tax 10%]]+FatmaUsf[[#This Row],[Bonus 3%]] -> 6089.64 | V2: =IF(FatmaUsf[[#This Row],[Net Salary]]>=6000,"Over","Normal") -> Over | W2: =VLOOKUP(FatmaUsf[[#This Row],[Net Salary]],$Z$10:$AA$14,2) -> 0.02
A3: 1002 | B3: OmAr | C3: hisham | D3: =PROPER(TRIM(FatmaUsf[[#This Row],[Last Name]]&" "&FatmaUsf[[#This Row],[Last Name]])) -> Hisham Hisham | E3: Male | F3: 011 2304-6179 | G3: Syria | H3: Contract | I3: Marketing | J3: Hawala | K3: o.hishan@email.com | L3: 6 | M3: 1 | N3: 2001 | O3: =DATE(FatmaUsf[[#This Row],[Hire Year]],FatmaUsf[[#This Row],[Hire Month]],FatmaUsf[[#This Row],[Hire Day]]) -> 36897 | P3: =TODAY() -> 46071 | Q3: =DATEDIF(FatmaUsf[[#This Row],[Hiring Date]],FatmaUsf[[#This Row],[current date]],"Y") -> 25 | R3: 7175 | S3: =FatmaUsf[[#This Row],[Salary]]*0.1 -> 717.5 | T3: =FatmaUsf[[#This Row],[Salary]]*0.03 -> 215.25 | U3: =FatmaUsf[[#This Row],[Salary]]-FatmaUsf[[#This Row],[Tax 10%]]+FatmaUsf[[#This Row],[Bonus 3%]] -> 6672.75 | V3: =IF(FatmaUsf[[#This Row],[Net Salary]]>=6000,"Over","Normal") -> Over | W3: =VLOOKUP(FatmaUsf[[#This Row],[Net Salary]],$Z$10:$AA$14,2) -> 0.02 | Z3: Total Net | AA3: =SUM(FatmaUsf[Net Salary]) -> 1242807.4
A4: 1003 | B4: Ailya | C4: ShaRaf | D4: =PROPER(TRIM(FatmaUsf[[#This Row],[Last Name]]&" "&FatmaUsf[[#This Row],[Last Name]])) -> Sharaf Sharaf | E4: Female | F4: 012 4071-7821 | G4: Saudi Arabia | H4: Half-Time | I4: Manufacturing | J4: Debt Card | K4: a.sharaf@email.com | L4: 7 | M4: 1 | N4: 2007 | O4: =DATE(FatmaUsf[[#This Row],[Hire Year]],FatmaUsf[[#This Row],[Hire Month]],FatmaUsf[[#This Row],[Hire Day]]) -> 39089 | P4: =TODAY() -> 46071 | Q4: =DATEDIF(FatmaUsf[[#This Row],[Hiring Date]],FatmaUsf[[#This Row],[current date]],"Y") -> 19 | R4: 4070 | S4: =FatmaUsf[[#This Row],[Salary]]*0.1 -> 407 | T4: =FatmaUsf[[#This Row],[Salary]]*0.03 -> 122.1 | U4: =FatmaUsf[[#This Row],[Salary]]-FatmaUsf[[#This Row],[Tax 10%]]+FatmaUsf[[#This Row],[Bonus 3%]] -> 3785.1 | V4: =IF(FatmaUsf[[#This Row],[Net Salary]]>=6000,"Over","Normal") -> Normal | W4: =VLOOKUP(FatmaUsf[[#This Row],[Net Salary]],$Z$10:$AA$14,2) -> 0.05 | Z4: Average Net | AA4: =AVERAGE(U:U) -> 4142.6912
A5: 1004 | B5: Lwiy | C5: Qbany | D5: =PROPER(TRIM(FatmaUsf[[#This Row],[Last Name]]&" "&FatmaUsf[[#This Row],[Last Name]])) -> Qbany Qbany | E5: Male | F5: 010 5618-2492 | G5: Sudan | H5: Full Time | I5: Account Management | J5: Hawala | K5: l.qbany@email.com | L5: 21 | M5: 1 | N5: 1993 | O5: =DATE(FatmaUsf[[#This Row],[Hire Year]],FatmaUsf[[#This Row],[Hire Month]],FatmaUsf[[#This Row],[Hire Day]]) -> 33990 | P5: =TODAY() -> 46071 | Q5: =DATEDIF(FatmaUsf[[#This Row],[Hiring Date]],FatmaUsf[[#This Row],[current date]],"Y") -> 33 | R5: 1906 | S5: =FatmaUsf[[#This Row],[Salary]]*0.1 -> 190.6 | T5: =FatmaUsf[[#This Row],[Salary]]*0.03 -> 57.18 | U5: =FatmaUsf[[#This Row],[Salary]]-FatmaUsf[[#This Row],[Tax 10%]]+FatmaUsf[[#This Row],[Bonus 3%]] -> 1772.58 | V5: =IF(FatmaUsf[[#This Row],[Net Salary]]>=6000,"Over","Normal") -> Normal | W5: =VLOOKUP(FatmaUsf[[#This Row],[Net Salary]],$Z$10:$AA$14,2) -> 0.08 | Z5: Count of Emp. | AA5: =COUNT(A:A) -> 300
A6: 1005 | B6: Ahmad | C6: bikri | D6: =PROPER(TRIM(FatmaUsf[[#This Row],[Last Name]]&" "&FatmaUsf[[#This Row],[Last Name]])) -> Bikri Bikri | E6: Male | F6: 011 7329-6122 | G6: Egypt | H6: Half-Time | I6: Account Management | J6: Hawala | K6: a.bikri@email.com | L6: 26 | M6: 1 | N6: 2019 | O6: =DATE(FatmaUsf[[#This Row],[Hire Year]],FatmaUsf[[#This Row],[Hire Month]],FatmaUsf[[#This Row],[Hire Day]]) -> 43491 | P6: =TODAY() -> 46071 | Q6: =DATEDIF(FatmaUsf[[#This Row],[Hiring Date]],FatmaUsf[[#This Row],[current date]],"Y") -> 7 | R6: 2600 | S6: =FatmaUsf[[#This Row],[Salary]]*0.1 -> 260 | T6: =FatmaUsf[[#This Row],[Salary]]*0.03 -> 78 | U6: =FatmaUsf[[#This Row],[Salary]]-FatmaUsf[[#This Row],[Tax 10%]]+FatmaUsf[[#This Row],[Bonus 3%]] -> 2418 | V6: =IF(FatmaUsf[[#This Row],[Net Salary]]>=6000,"Over","Normal") -> Normal | W6: =VLOOKUP(FatmaUsf[[#This Row],[Net Salary]],$Z$10:$AA$14,2) -> 0.08 | Z6: Max Salary | AA6: =MAX(R:R) -> 7478
A7: 1006 | B7: Muhamad | C7: Zueitr | D7: =PROPER(TRIM(FatmaUsf[[#This Row],[Last Name]]&" "&FatmaUsf[[#This Row],[Last Name]])) -> Zueitr Zueitr | E7: Male | F7: 011 2527-4512 | G7: Saudi Arabia | H7: Contract | I7: Quality Control | J7: Hawala | K7: m.zueitr@email.com | L7: 26 | M7: 1 | N7: 2003 | O7: =DATE(FatmaUsf[[#This Row],[Hire Year]],FatmaUsf[[#This Row],[Hire Month]],FatmaUsf[[#This Row],[Hire Day]]) -> 37647 | P7: =TODAY() -> 46071 | Q7: =DATEDIF(FatmaUsf[[#This Row],[Hiring Date]],FatmaUsf[[#This Row],[current date]],"Y") -> 23 | R7: 3753 | S7: =FatmaUsf[[#This Row],[Salary]]*0.1 -> 375.3 | T7: =FatmaUsf[[#This Row],[Salary]]*0.03 -> 112.59 | U7: =FatmaUsf[[#This Row],[Salary]]-FatmaUsf[[#This Row],[Tax 10%]]+FatmaUsf[[#This Row],[Bonus 3%]] -> 3490.29 | V7: =IF(FatmaUsf[[#This Row],[Net Salary]]>=6000,"Over","Normal") -> Normal | W7: =VLOOKUP(FatmaUsf[[#This Row],[Net Salary]],$Z$10:$AA$14,2) -> 0.05 | Z7: Min Salary | AA7: =MIN(R:R) -> 742
A8: 1007 | B8: Iin | C8: Alhalaliu | D8: =PROPER(TRIM(FatmaUsf[[#This Row],[Last Name]]&" "&FatmaUsf[[#This Row],[Last Name]])) -> Alhalaliu Alhalaliu | E8: Female | F8: 012 2640-9521 | G8: Iraq | H8: Full Time | I8: Engineering | J8: Master Card | K8: i.alhalaliu@email.com | L8: 29 | M8: 1 | N8: 1994 | O8: =DATE(FatmaUsf[[#This Row],[Hire Year]],FatmaUsf[[#This Row],[Hire Month]],FatmaUsf[[#This Row],[Hire Day]]) -> 34363 | P8: =TODAY() -> 46071 | Q8: =DATEDIF(FatmaUsf[[#This Row],[Hiring Date]],FatmaUsf[[#This Row],[current date]],"Y") -> 32 | R8: 5086 | S8: =FatmaUsf[[#This Row],[Salary]]*0.1 -> 508.6 | T8: =FatmaUsf[[#This Row],[Salary]]*0.03 -> 152.58 | U8: =FatmaUsf[[#This Row],[Salary]]-FatmaUsf[[#This Row],[Tax 10%]]+FatmaUsf[[#This Row],[Bonus 3%]] -> 4729.98 | V8: =IF(FatmaUsf[[#This Row],[Net Salary]]>=6000,"Over","Normal") -> Normal | W8: =VLOOKUP(FatmaUsf[[#This Row],[Net Salary]],$Z$10:$AA$14,2) -> 0.05
A9: 1008 | B9: Muhamad | C9: Alaya | D9: =PROPER(TRIM(FatmaUsf[[#This Row],[Last Name]]&" "&FatmaUsf[[#This Row],[Last Name]])) -> Alaya Alaya | E9: Male | F9: 010 8241-1311 | G9: Saudi Arabia | H9: Hourly | I9: Manufacturing | J9: Western Union | K9: m.alaya@email.com | L9: 29 | M9: 1 | N9: 2012 | O9: =DATE(FatmaUsf[[#This Row],[Hire Year]],FatmaUsf[[#This Row],[Hire Month]],FatmaUsf[[#This Row],[Hire Day]]) -> 40937 | P9: =TODAY() -> 46071 | Q9: =DATEDIF(FatmaUsf[[#This Row],[Hiring Date]],FatmaUsf[[#This Row],[current date]],"Y") -> 14 | R9: 2431 | S9: =FatmaUsf[[#This Row],[Salary]]*0.1 -> 243.1 | T9: =FatmaUsf[[#This Row],[Salary]]*0.03 -> 72.93 | U9: =FatmaUsf[[#This Row],[Salary]]-FatmaUsf[[#This Row],[Tax 10%]]+FatmaUsf[[#This Row],[Bonus 3%]] -> 2260.83 | V9: =IF(FatmaUsf[[#This Row],[Net Salary]]>=6000,"Over","Normal") -> Normal | W9: =VLOOKUP(FatmaUsf[[#This Row],[Net Salary]],$Z$10:$AA$14,2) -> 0.08
A10: 1009 | B10: Susin | C10: Almilat | D10: =PROPER(TRIM(FatmaUsf[[#This Row],[Last Name]]&" "&FatmaUsf[[#This Row],[Last Name]])) -> Almilat Almilat | E10: Female | F10: 012 1039-8810 | G10: Egypt | H10: Full Time | I10: Manufacturing | J10: Hawala | K10: s.almilat@email.com | L10: 30 | M10: 1 | N10: 2004 | O10: =DATE(FatmaUsf[[#This Row],[Hire Year]],FatmaUsf[[#This Row],[Hire Month]],FatmaUsf[[#This Row],[Hire Day]]) -> 38016 | P10: =TODAY() -> 46071 | Q10: =DATEDIF(FatmaUsf[[#This Row],[Hiring Date]],FatmaUsf[[#This Row],[current date]],"Y") -> 22 | R10: 2955 | S10: =FatmaUsf[[#This Row],[Salary]]*0.1 -> 295.5 | T10: =FatmaUsf[[#This Row],[Salary]]*0.03 -> 88.65 | U10: =FatmaUsf[[#This Row],[Salary]]-FatmaUsf[[#This Row],[Tax 10%]]+FatmaUsf[[#This Row],[Bonus 3%]] -> 2748.15 | V10: =IF(FatmaUsf[[#This Row],[Net Salary]]>=6000,"Over","Normal") -> Normal | W10: =VLOOKUP(FatmaUsf[[#This Row],[Net Salary]],$Z$10:$AA$14,2) -> 0.08 | Z10: Salary | AA10: Extra Bonus %
A11: 1010 | B11: Muhamad | C11: Alrifaei | D11: =PROPER(TRIM(FatmaUsf[[#This Row],[Last Name]]&" "&FatmaUsf[[#This Row],[Last Name]])) -> Alrifaei Alrifaei | E11: Male | F11: 010 7467-7662 | G11: Egypt | H11: Half-Time | I11: Engineering | J11: Hawala | K11: m.alrifaei@email.com | L11: 11 | M11: 2 | N11: 2003 | O11: =DATE(FatmaUsf[[#This Row],[Hire Year]],FatmaUsf[[#This Row],[Hire Month]],FatmaUsf[[#This Row],[Hire Day]]) -> 37663 | P11: =TODAY() -> 46071 | Q11: =DATEDIF(FatmaUsf[[#This Row],[Hiring Date]],FatmaUsf[[#This Row],[current date]],"Y") -> 23 | R11: 1948 | S11: =FatmaUsf[[#This Row],[Salary]]*0.1 -> 194.8 | T11: =FatmaUsf[[#This Row],[Salary]]*0.03 -> 58.44 | U11: =FatmaUsf[[#This Row],[Salary]]-FatmaUsf[[#This Row],[Tax 10%]]+FatmaUsf[[#This Row],[Bonus 3%]] -> 1811.64 | V11: =IF(FatmaUsf[[#This Row],[Net Salary]]>=6000,"Over","Normal") -> Normal | W11: =VLOOKUP(FatmaUsf[[#This Row],[Net Salary]],$Z$10:$AA$14,2) -> 0.08 | Z11: 1 | AA11: 0.1
A12: 1011 | B12: Muhamad | C12: Alqadah | D12: =PROPER(TRIM(FatmaUsf[[#This Row],[Last Name]]&" "&FatmaUsf[[#This Row],[Last Name]])) -> Alqadah Alqadah | E12: Male | F12: 011 8317-7634 | G12: Iraq | H12: Half-Time | I12: Marketing | J12: Western Union | K12: m.alqadah@email.com | L12: 11 | M12: 2 | N12: 1993 | O12: =DATE(FatmaUsf[[#This Row],[Hire Year]],FatmaUsf[[#This Row],[Hire Month]],FatmaUsf[[#This Row],[Hire Day]]) -> 34011 | P12: =TODAY() -> 46071 | Q12: =DATEDIF(FatmaUsf[[#This Row],[Hiring Date]],FatmaUsf[[#This Row],[current date]],"Y") -> 33 | R12: 3294 | S12: =FatmaUsf[[#This Row],[Salary]]*0.1 -> 329.4 | T12: =FatmaUsf[[#This Row],[Salary]]*0.03 -> 98.82 | U12: =FatmaUsf[[#This Row],[Salary]]-FatmaUsf[[#This Row],[Tax 10%]]+FatmaUsf[[#This Row],[Bonus 3%]] -> 3063.42 | V12: =IF(FatmaUsf[[#This Row],[Net Salary]]>=6000,"Over","Normal") -> Normal | W12: =VLOOKUP(FatmaUsf[[#This Row],[Net Salary]],$Z$10:$AA$14,2) -> 0.05 | Z12: 1000 | AA12: 0.08
A13: 1012 | B13: Muhamad | C13: Iad | D13: =PROPER(TRIM(FatmaUsf[[#This Row],[Last Name]]&" "&FatmaUsf[[#This Row],[Last Name]])) -> Iad Iad | E13: Male | F13: 011 6548-2919 | G13: Sudan | H13: Contract | I13: Engineering | J13: Debt Card | K13: m.iad@email.com | L13: 17 | M13: 2 | N13: 2005 | O13: =DATE(FatmaUsf[[#This Row],[Hire Year]],FatmaUsf[[#This Row],[Hire Month]],FatmaUsf[[#This Row],[Hire Day]]) -> 38400 | P13: =TODAY() -> 46071 | Q13: =DATEDIF(FatmaUsf[[#This Row],[Hiring Date]],FatmaUsf[[#This Row],[current date]],"Y") -> 21 | R13: 7123 | S13: =FatmaUsf[[#This Row],[Salary]]*0.1 -> 712.3 | T13: =FatmaUsf[[#This Row],[Salary]]*0.03 -> 213.69 | U13: =FatmaUsf[[#This Row],[Salary]]-FatmaUsf[[#This Row],[Tax 10%]]+FatmaUsf[[#This Row],[Bonus 3%]] -> 6624.39 | V13: =IF(FatmaUsf[[#This Row],[Net Salary]]>=6000,"Over","Normal") -> Over | W13: =VLOOKUP(FatmaUsf[[#This Row],[Net Salary]],$Z$10:$AA$14,2) -> 0.02 | Z13: 3000 | AA13: 0.05
A14: 1013 | B14: Razaan | C14: Nasif | D14: =PROPER(TRIM(FatmaUsf[[#This Row],[Last Name]]&" "&FatmaUsf[[#This Row],[Last Name]])) -> Nasif Nasif | E14: Female | F14: 010 6241-6559 | G14: Saudi Arabia | H14: Full Time | I14: Marketing | J14: Debt Card | K14: r.nasif@email.com | L14: 25 | M14: 2 | N14: 2019 | O14: =DATE(FatmaUsf[[#This Row],[Hire Year]],FatmaUsf[[#This Row],[Hire Month]],FatmaUsf[[#This Row],[Hire Day]]) -> 43521 | P14: =TODAY() -> 46071 | Q14: =DATEDIF(FatmaUsf[[#This Row],[Hiring Date]],FatmaUsf[[#This Row],[current date]],"Y") -> 6 | R14: 7236 | S14: =FatmaUsf[[#This Row],[Salary]]*0.1 -> 723.6 | T14: =FatmaUsf[[#This Row],[Salary]]*0.03 -> 217.08 | U14: =FatmaUsf[[#This Row],[Salary]]-FatmaUsf[[#This Row],[Tax 10%]]+FatmaUsf[[#This Row],[Bonus 3%]] -> 6729.48 | V14: =IF(FatmaUsf[[#This Row],[Net Salary]]>=6000,"Over","Normal") -> Over | W14: =VLOOKUP(FatmaUsf[[#This Row],[Net Salary]],$Z$10:$AA$14,2) -> 0.02 | Z14: 6000 | AA14: 0.02
A15: 1014 | B15: Iilian | C15: mohamed | D15: =PROPER(TRIM(FatmaUsf[[#This Row],[Last Name]]&" "&FatmaUsf[[#This Row],[Last Name]])) -> Mohamed Mohamed | E15: Female | F15: 012 0080-0351 | G15: Sudan | H15: Full Time | I15: Engineering | J15: Hawala | K15: i.dbs@email.com | L15: 26 | M15: 2 | N15: 2004 | O15: =DATE(FatmaUsf[[#This Row],[Hire Year]],FatmaUsf[[#This Row],[Hire Month]],FatmaUsf[[#This Row],[Hire Day]]) -> 38043 | P15: =TODAY() -> 46071 | Q15: =DATEDIF(FatmaUsf[[#This Row],[Hiring Date]],FatmaUsf[[#This Row],[current date]],"Y") -> 21 | R15: 6843 | S15: =FatmaUsf[[#This Row],[Salary]]*0.1 -> 684.3 | T15: =FatmaUsf[[#This Row],[Salary]]*0.03 -> 205.29 | U15: =FatmaUsf[[#This Row],[Salary]]-FatmaUsf[[#This Row],[Tax 10%]]+FatmaUsf[[#This Row],[Bonus 3%]] -> 6363.99 | V15: =IF(FatmaUsf[[#This Row],[Net Salary]]>=6000,"Over","Normal") -> Over | W15: =VLOOKUP(FatmaUsf[[#This Row],[Net Salary]],$Z$10:$AA$14,2) -> 0.02
A16: 1015 | B16: Bayan | C16: mostafa | D16: =PROPER(TRIM(FatmaUsf[[#This Row],[Last Name]]&" "&FatmaUsf[[#This Row],[Last Name]])) -> Mostafa Mostafa | E16: Female | F16: 011 5953-5296 | G16: Sudan | H16: Hourly | I16: Engineering | J16: Hawala | K16: b.qdw@email.com | L16: 2 | M16: 3 | N16: 2011 | O16: =DATE(FatmaUsf[[#This Row],[Hire Year]],FatmaUsf[[#This Row],[Hire Month]],FatmaUsf[[#This Row],[Hire Day]]) -> 40604 | P16: =TODAY() -> 46071 | Q16: =DATEDIF(FatmaUsf[[#This Row],[Hiring Date]],FatmaUsf[[#This Row],[current date]],"Y") -> 14 | R16: 1070 | S16: =FatmaUsf[[#This Row],[Salary]]*0.1 -> 107 | T16: =FatmaUsf[[#This Row],[Salary]]*0.03 -> 32.1 | U16: =FatmaUsf[[#This Row],[Salary]]-FatmaUsf[[#This Row],[Tax 10%]]+FatmaUsf[[#This Row],[Bonus 3%]] -> 995.1 | V16: =IF(FatmaUsf[[#This Row],[Net Salary]]>=6000,"Over","Normal") -> Normal | W16: =VLOOKUP(FatmaUsf[[#This Row],[Net Salary]],$Z$10:$AA$14,2) -> 0.1
A17: 1016 | B17: Alaa | C17: Muhamad | D17: =PROPER(TRIM(FatmaUsf[[#This Row],[Last Name]]&" "&FatmaUsf[[#This Row],[Last Name]])) -> Muhamad Muhamad | E17: Male | F17: 010 5319-7669 | G17: Saudi Arabia | H17: Hourly | I17: Engineering | J17: Debt Card | K17: a.muhamad@email.com | L17: 10 | M17: 3 | N17: 2020 | O17: =DATE(FatmaUsf[[#This Row],[Hire Year]],FatmaUsf[[#This Row],[Hire Month]],FatmaUsf[[#This Row],[Hire Day]]) -> 43900 | P17: =TODAY() -> 46071 | Q17: =DATEDIF(FatmaUsf[[#This Row],[Hiring Date]],FatmaUsf[[#This Row],[current date]],"Y") -> 5 | R17: 1493 | S17: =FatmaUsf[[#This Row],[Salary]]*0.1 -> 149.3 | T17: =FatmaUsf[[#This Row],[Salary]]*0.03 -> 44.79 | U17: =FatmaUsf[[#This Row],[Salary]]-FatmaUsf[[#This Row],[Tax 10%]]+FatmaUsf[[#This Row],[Bonus 3%]] -> 1388.49 | V17: =IF(FatmaUsf[[#This Row],[Net Salary]]>=6000,"Over","Normal") -> Normal | W17: =VLOOKUP(FatmaUsf[[#This Row],[Net Salary]],$Z$10:$AA$14,2) -> 0.08
A18: 1017 | B18: Sandra | C18: Ziad | D18: =PROPER(TRIM(FatmaUsf[[#This Row],[Last Name]]&" "&FatmaUsf[[#This Row],[Last Name]])) -> Ziad Ziad | E18: Female | F18: 011 2332-0982 | G18: Iraq | H18: Full Time | I18: Marketing | J18: Hawala | K18: s.ziad@email.com | L18: 6 | M18: 4 | N18: 1999 | O18: =DATE(FatmaUsf[[#This Row],[Hire Year]],FatmaUsf[[#This Row],[Hire Month]],FatmaUsf[[#This Row],[Hire Day]]) -> 36256 | P18: =TODAY() -> 46071 | Q18: =DATEDIF(FatmaUsf[[#This Row],[Hiring Date]],FatmaUsf[[#This Row],[current date]],"Y") -> 26 | R18: 5857 | S18: =FatmaUsf[[#This Row],[Salary]]*0.1 -> 585.7 | T18: =FatmaUsf[[#This Row],[Salary]]*0.03 -> 175.71 | U18: =FatmaUsf[[#This Row],[Salary]]-FatmaUsf[[#This Row],[Tax 10%]]+FatmaUsf[[#This Row],[Bonus 3%]] -> 5447.01 | V18: =IF(FatmaUsf[[#This Row],[Net Salary]]>=6000,"Over","Normal") -> Normal | W18: =VLOOKUP(FatmaUsf[[#This Row],[Net Salary]],$Z$10:$AA$14,2) -> 0.05
A19: 1018 | B19: Farahad | C19: Husayn | D19: =PROPER(TRIM(FatmaUsf[[#This Row],[Last Name]]&" "&FatmaUsf[[#This Row],[Last Name]])) -> Husayn Husayn | E19: Male | F19: 010 1442-5932 | G19: Iraq | H19: Contract | I19: IT | J19: Hawala | K19: f.husayn@email.com | L19: 12 | M19: 4 | N19: 2004 | O19: =DATE(FatmaUsf[[#This Row],[Hire Year]],FatmaUsf[[#This Row],[Hire Month]],FatmaUsf[[#This Row],[Hire Day]]) -> 38089 | P19: =TODAY() -> 46071 | Q19: =DATEDIF(FatmaUsf[[#This Row],[Hiring Date]],FatmaUsf[[#This Row],[current date]],"Y") -> 21 | R19: 5278 | S19: =FatmaUsf[[#This Row],[Salary]]*0.1 -> 527.8 | T19: =FatmaUsf[[#This Row],[Salary]]*0.03 -> 158.34 | U19: =FatmaUsf[[#This Row],[Salary]]-FatmaUsf[[#This Row],[Tax 10%]]+FatmaUsf[[#This Row],[Bonus 3%]] -> 4908.54 | V19: =IF(FatmaUsf[[#This Row],[Net Salary]]>=6000,"Over","Normal") -> Normal | W19: =VLOOKUP(FatmaUsf[[#This Row],[Net Salary]],$Z$10:$AA$14,2) -> 0.05
A20: 1019 | B20: Ahed | C20: Salim | D20: =PROPER(TRIM(FatmaUsf[[#This Row],[Last Name]]&" "&FatmaUsf[[#This Row],[Last Name]])) -> Salim Salim | E20: Female | F20: 011 6732-2351 | G20: Sudan | H20: Full Time | I20: IT | J20: Hawala | K20: a.salim@email.com | L20: 13 | M20: 4 | N20: 1999 | O20: =DATE(FatmaUsf[[#This Row],[Hire Year]],FatmaUsf[[#This Row],[Hire Month]],FatmaUsf[[#This Row],[Hire Day]]) -> 36263 | P20: =TODAY() -> 46071 | Q20: =DATEDIF(FatmaUsf[[#This Row],[Hiring Date]],FatmaUsf[[#This Row],[current date]],"Y") -> 26 | R20: 5710 | S20: =FatmaUsf[[#This Row],[Salary]]*0.1 -> 571 | T20: =FatmaUsf[[#This Row],[Salary]]*0.03 -> 171.3 | U20: =FatmaUsf[[#This Row],[Salary]]-FatmaUsf[[#This Row],[Tax 10%]]+FatmaUsf[[#This Row],[Bonus 3%]] -> 5310.3 | V20: =IF(FatmaUsf[[#This Row],[Net Salary]]>=6000,"Over","Normal") -> Normal | W20: =VLOOKUP(FatmaUsf[[#This Row],[Net Salary]],$Z$10:$AA$14,2) -> 0.05
A21: 1020 | B21: Ayham | C21: Tutwnji | D21: =PROPER(TRIM(FatmaUsf[[#This Row],[Last Name]]&" "&FatmaUsf[[#This Row],[Last Name]])) -> Tutwnji Tutwnji | E21: Male | F21: 011 8295-8045 | G21: Saudi Arabia | H21: Full Time | I21: Account Management | J21: Hawala | K21: a.tutwnji@email.com | L21: 28 | M21: 4 | N21: 2020 | O21: =DATE(FatmaUsf[[#This Row],[Hire Year]],FatmaUsf[[#This Row],[Hire Month]],FatmaUsf[[#This Row],[Hire Day]]) -> 43949 | P21: =TODAY() -> 46071 | Q21: =DATEDIF(FatmaUsf[[#This Row],[Hiring Date]],FatmaUsf[[#This Row],[current date]],"Y") -> 5 | R21: 6145 | S21: =FatmaUsf[[#This Row],[Salary]]*0.1 -> 614.5 | T21: =FatmaUsf[[#This Row],[Salary]]*0.03 -> 184.35 | U21: =FatmaUsf[[#This Row],[Salary]]-FatmaUsf[[#This Row],[Tax 10%]]+FatmaUsf[[#This Row],[Bonus 3%]] -> 5714.85 | V21: =IF(FatmaUsf[[#This Row],[Net Salary]]>=6000,"Over","Normal") -> Normal | W21: =VLOOKUP(FatmaUsf[[#This Row],[Net Salary]],$Z$10:$AA$14,2) -> 0.05
A22: 1021 | B22: Samir | C22: Alsafdi | D22: =PROPER(TRIM(FatmaUsf[[#This Row],[Last Name]]&" "&FatmaUsf[[#This Row],[Last Name]])) -> Alsafdi Alsafdi | E22: Male | F22: 010 8655-8298 | G22: Egypt | H22: Contract | I22: IT | J22: Western Union | K22: s.alsafdi@email.com | L22: 1 | M22: 5 | N22: 2012 | O22: =DATE(FatmaUsf[[#This Row],[Hire Year]],FatmaUsf[[#This Row],[Hire Month]],FatmaUsf[[#This Row],[Hire Day]]) -> 41030 | P22: =TODAY() -> 46071 | Q22: =DATEDIF(FatmaUsf[[#This Row],[Hiring Date]],FatmaUsf[[#This Row],[current date]],"Y") -> 13 | R22: 5278 | S22: =FatmaUsf[[#This Row],[Salary]]*0.1 -> 527.8 | T22: =FatmaUsf[[#This Row],[Salary]]*0.03 -> 158.34 | U22: =FatmaUsf[[#This Row],[Salary]]-FatmaUsf[[#This Row],[Tax 10%]]+FatmaUsf[[#This Row],[Bonus 3%]] -> 4908.54 | V22: =IF(FatmaUsf[[#This Row],[Net Salary]]>=6000,"Over","Normal") -> Normal | W22: =VLOOKUP(FatmaUsf[[#This Row],[Net Salary]],$Z$10:$AA$14,2) -> 0.05
A23: 1022 | B23: Bilal | C23: Jalal | D23: =PROPER(TRIM(FatmaUsf[[#This Row],[Last Name]]&" "&FatmaUsf[[#This Row],[Last Name]])) -> Jalal Jalal | E23: Male | F23: 010 2145-8500 | G23: Egypt | H23: Contract | I23: Manufacturing | J23: Debt Card | K23: b.jalal@email.com | L23: 7 | M23: 5 | N23: 1996 | O23: =DATE(FatmaUsf[[#This Row],[Hire Year]],FatmaUsf[[#This Row],[Hire Month]],FatmaUsf[[#This Row],[Hire Day]]) -> 35192 | P23: =TODAY() -> 46071 | Q23: =DATEDIF(FatmaUsf[[#This Row],[Hiring Date]],FatmaUsf[[#This Row],[current date]],"Y") -> 29 | R23: 6409 | S23: =FatmaUsf[[#This Row],[Salary]]*0.1 -> 640.9 | T23: =FatmaUsf[[#This Row],[Salary]]*0.03 -> 192.27 | U23: =FatmaUsf[[#This Row],[Salary]]-FatmaUsf[[#This Row],[Tax 10%]]+FatmaUsf[[#This Row],[Bonus 3%]] -> 5960.37 | V23: =IF(FatmaUsf[[#This Row],[Net Salary]]>=6000,"Over","Normal") -> Normal | W23: =VLOOKUP(FatmaUsf[[#This Row],[Net Salary]],$Z$10:$AA$14,2) -> 0.05
A24: 1023 | B24: Riad | C24: Sahalul | D24: =PROPER(TRIM(FatmaUsf[[#This Row],[Last Name]]&" "&FatmaUsf[[#This Row],[Last Name]])) -> Sahalul Sahalul | E24: Male | F24: 010 3436-0371 | G24: Saudi Arabia | H24: Full Time | I24: Manufacturing | J24: Hawala | K24: r.sahalul@email.com | L24: 12 | M24: 5 | N24: 2007 | O24: =DATE(FatmaUsf[[#This Row],[Hire Year]],FatmaUsf[[#This Row],[Hire Month]],FatmaUsf[[#This Row],[Hire Day]]) -> 39214 | P24: =TODAY() -> 46071 | Q24: =DATEDIF(FatmaUsf[[#This Row],[Hiring Date]],FatmaUsf[[#This Row],[current date]],"Y") -> 18 | R24: 7478 | S24: =FatmaUsf[[#This Row],[Salary]]*0.1 -> 747.8 | T24: =FatmaUsf[[#This Row],[Salary]]*0.03 -> 224.34 | U24: =FatmaUsf[[#This Row],[Salary]]-FatmaUsf[[#This Row],[Tax 10%]]+FatmaUsf[[#This Row],[Bonus 3%]] -> 6954.54 | V24: =IF(FatmaUsf[[#This Row],[Net Salary]]>=6000,"Over","Normal") -> Over | W24: =VLOOKUP(FatmaUsf[[#This Row],[Net Salary]],$Z$10:$AA$14,2) -> 0.02
A25: 1024 | B25: Ahmad | C25: Ahmad | D25: =PROPER(TRIM(FatmaUsf[[#This Row],[Last Name]]&" "&FatmaUsf[[#This Row],[Last Name]])) -> Ahmad Ahmad | E25: Male | F25: 011 2766-3217 | G25: Sudan | H25: Full Time | I25: Manufacturing | J25: Master Card | K25: a.ahmad@email.com | L25: 18 | M25: 5 | N25: 2002 | O25: =DATE(FatmaUsf[[#This Row],[Hire Year]],FatmaUsf[[#This Row],[Hire Month]],FatmaUsf[[#This Row],[Hire Day]]) -> 37394 | P25: =TODAY() -> 46071 | Q25: =DATEDIF(FatmaUsf[[#This Row],[Hiring Date]],FatmaUsf[[#This Row],[current date]],"Y") -> 23 | R25: 4621 | S25: =FatmaUsf[[#This Row],[Salary]]*0.1 -> 462.1 | T25: =FatmaUsf[[#This Row],[Salary]]*0.03 -> 138.63 | U25: =FatmaUsf[[#This Row],[Salary]]-FatmaUsf[[#This Row],[Tax 10%]]+FatmaUsf[[#This Row],[Bonus 3%]] -> 4297.53 | V25: =IF(FatmaUsf[[#This Row],[Net Salary]]>=6000,"Over","Normal") -> Normal | W25: =VLOOKUP(FatmaUsf[[#This Row],[Net Salary]],$Z$10:$AA$14,2) -> 0.05
A26: 1025 | B26: Muhamad | C26: Altarah | D26: =PROPER(TRIM(FatmaUsf[[#This Row],[Last Name]]&" "&FatmaUsf[[#This Row],[Last Name]])) -> Altarah Altarah | E26: Male | F26: 012 3389-6143 | G26: Egypt | H26: Contract | I26: Product Development | J26: Master Card | K26: m.altarah@email.com | L26: 19 | M26: 5 | N26: 2002 | O26: =DATE(FatmaUsf[[#This Row],[Hire Year]],FatmaUsf[[#This Row],[Hire Month]],FatmaUsf[[#This Row],[Hire Day]]) -> 37395 | P26: =TODAY() -> 46071 | Q26: =DATEDIF(FatmaUsf[[#This Row],[Hiring Date]],FatmaUsf[[#This Row],[current date]],"Y") -> 23 | R26: 2093 | S26: =FatmaUsf[[#This Row],[Salary]]*0.1 -> 209.3 | T26: =FatmaUsf[[#This Row],[Salary]]*0.03 -> 62.79 | U26: =FatmaUsf[[#This Row],[Salary]]-FatmaUsf[[#This Row],[Tax 10%]]+FatmaUsf[[#This Row],[Bonus 3%]] -> 1946.49 | V26: =IF(FatmaUsf[[#This Row],[Net Salary]]>=6000,"Over","Normal") -> Normal | W26: =VLOOKUP(FatmaUsf[[#This Row],[Net Salary]],$Z$10:$AA$14,2) -> 0.08
... A301: 1300 | B301: Ahmad | C301: Qadimati | D301: =PROPER(TRIM(FatmaUsf[[#This Row],[Last Name]]&" "&FatmaUsf[[#This Row],[Last Name]])) -> Qadimati Qadimati | E301: Male | F301: 011 5056-6641 | G301: Iraq | H301: Full Time | I301: Marketing | J301: Western Union | K301: a.qadimati@email.com | L301: 8 | M301: 3 | N301: 2015 | O301: =DATE(FatmaUsf[[#This Row],[Hire Year]],FatmaUsf[[#This Row],[Hire Month]],FatmaUsf[[#This Row],[Hire Day]]) -> 42071 | P301: =TODAY() -> 46071 | Q301: =DATEDIF(FatmaUsf[[#This Row],[Hiring Date]],FatmaUsf[[#This Row],[current date]],"Y") -> 10 | R301: 3294 | S301: =FatmaUsf[[#This Row],[Salary]]*0.1 -> 329.4 | T301: =FatmaUsf[[#This Row],[Salary]]*0.03 -> 98.82 | U301: =FatmaUsf[[#This Row],[Salary]]-FatmaUsf[[#This Row],[Tax 10%]]+FatmaUsf[[#This Row],[Bonus 3%]] -> 3063.42 | V301: =IF(FatmaUsf[[#This Row],[Net Salary]]>=6000,"Over","Normal") -> Normal | W301: =VLOOKUP(FatmaUsf[[#This Row],[Net Salary]],$Z$10:$AA$14,2) -> 0.05

Sheet Pivot
A3: Count of ID | B3: Sum of Net Salary | C3: Average of Experience Year | F3: Country | G3: Count of ID | J3: Count of ID | K3: Work Type | O3: Gender | P3: Count of ID | S3: MonyTransfere | T3: Count of ID | W3: Extra Bonus | X3: Count of ID | AA3: Hire Year | AB3: Sum of ID | AC3: Sum of Net Salary
A4: 300 | B4: 1242807.4 | C4: 19.146667 | F4: Egypt | G4: 99 | J4: Department | K4: Contract | L4: Full Time | M4: Half-Time | N4: Hourly | O4: Female | P4: 115 | S4: Debt Card | T4: 111 | W4: 0.02 | X4: 52 | AA4: 1990 | AB4: 8112 | AC4: 26916.06
F5: Iraq | G5: 53 | J5: Account Management | K5: 11 | L5: 21 | M5: 3 | N5: 4 | O5: Male | P5: 185 | S5: Hawala | T5: 92 | W5: 0.05 | X5: 150 | AA5: 1991 | AB5: 10666 | AC5: 38588.49
F6: Saudi Arabia | G6: 72 | J6: Creative | K6: 2 | L6: 2 | N6: 1 | S6: Master Card | T6: 44 | W6: 0.08 | X6: 84 | AA6: 1992 | AB6: 15659 | AC6: 49356.03
F7: Sudan | G7: 61 | J7: Engineering | K7: 18 | L7: 21 | M7: 10 | N7: 6 | S7: Western Union | T7: 53 | W7: 0.1 | X7: 14 | AA7: 1993 | AB7: 13458 | AC7: 44172.21
F8: Syria | G8: 15 | J8: IT | K8: 11 | L8: 9 | M8: 3 | N8: 1 | AA8: 1994 | AB8: 12530 | AC8: 54419.88
J9: Manufacturing | K9: 23 | L9: 30 | M9: 6 | N9: 12 | AA9: 1995 | AB9: 11569 | AC9: 37767.3
J10: Marketing | K10: 25 | L10: 24 | M10: 8 | N10: 8 | AA10: 1996 | AB10: 12664 | AC10: 44135.94
J11: Product Development | K11: 5 | L11: 5 | AA11: 1997 | AB11: 9212 | AC11: 20253.54
J12: Quality Control | K12: 6 | L12: 3 | M12: 3 | N12: 3 | AA12: 1998 | AB12: 6846 | AC12: 30495.63
J13: Sales | K13: 6 | L13: 6 | M13: 3 | N13: 1 | AA13: 1999 | AB13: 6384 | AC13: 35611.56
AA14: 2000 | AB14: 9400 | AC14: 26495.7
AA15: 2001 | AB15: 15269 | AC15: 40021.62
E16: =F3 -> Country | F16: =G3 -> Count of ID | AA16: 2002 | AB16: 12653 | AC16: 59696.7
E17: =F4 -> Egypt | F17: =G4 -> 99 | AA17: 2003 | AB17: 8119 | AC17: 31093.62
E18: =F5 -> Iraq | F18: =G5 -> 53 | AA18: 2004 | AB18: 13201 | AC18: 49900.08
E19: =F6 -> Saudi Arabia | F19: =G6 -> 72 | AA19: 2005 | AB19: 7740 | AC19: 25545.24
E20: =F7 -> Sudan | F20: =G7 -> 61 | AA20: 2006 | AB20: 6616 | AC20: 23720.58
E21: =F8 -> Syria | F21: =G8 -> 15 | AA21: 2007 | AB21: 8167 | AC21: 34134.72
AA22: 2008 | AB22: 11537 | AC22: 39246
AA23: 2009 | AB23: 5720 | AC23: 24770.55
AA24: 2010 | AB24: 9524 | AC24: 42225.72
AA25: 2011 | AB25: 13386 | AC25: 41767.23
AA26: 2012 | AB26: 10503 | AC26: 43816.95
AA27: 2013 | AB27: 9389 | AC27: 34353.27
AA28: 2014 | AB28: 9260 | AC28: 31633.95
AA29: 2015 | AB29: 10656 | AC29: 39567.78
AA30: 2016 | AB30: 6960 | AC30: 27471.27
AA31: 2017 | AB31: 9440 | AC31: 34286.31
AA32: 2018 | AB32: 11564 | AC32: 42804.18
AA33: 2019 | AB33: 11138 | AC33: 38161.62
... AA37: 2023 | AB37: 8117 | AC37: 29503.32

Sheet Range
A1: ID | B1: First Name | C1: Last Name | D1: Full Name | E1: Gender | F1: Phone | G1: Country | H1: Work Type | I1: Department | J1: MonyTransfere | K1: Email | L1: Hire Day | M1: Hire Month | N1: Hire Year | O1: Hiring Date | P1: current date | Q1: Experience Year | R1: Salary | S1: Tax 10% | T1: Bonus 3% | U1: Net Salary | V1: Salary Status | W1: Extra Bonus | Y1: = | Z1: Net >=6000 (Over) | AA1: Net <6000 (Normal)
A2: 1001 | B2: Ghadir | C2: AhmeD | D2: =PROPER(TRIM(Range!$C2&" "&Range!$C2)) -> Ahmed Ahmed | E2: Female | F2: 012 2910-2426 | G2: Sudan | H2: Full Time | I2: Manufacturing | J2: Debt Card | K2: g.ahmed@email.com | L2: 5 | M2: 4 | N2: 2023 | O2: =DATE(Range!$N2,Range!$M2,Range!$L2) -> 45021 | P2: =TODAY() -> 46071 | Q2: =DATEDIF(Range!$O2,Range!$P2,"Y") -> 2 | R2: 6548 | S2: =Range!$R2*0.1 -> 654.8 | T2: =Range!$R2*0.03 -> 196.44 | U2: =Range!$R2-Range!$S2+Range!$T2 -> 6089.64 | V2: =IF(Range!$U2>=6000,"Over","Normal") -> Over | W2: =VLOOKUP(Range!$U2,$Z$10:$AA$14,2) -> 0.02
A3: 1002 | B3: OmAr | C3: hisham | D3: =PROPER(TRIM(Range!$C3&" "&Range!$C3)) -> Hisham Hisham | E3: Male | F3: 011 2304-6179 | G3: Syria | H3: Contract | I3: Marketing | J3: Hawala | K3: o.hishan@email.com | L3: 6 | M3: 1 | N3: 2001 | O3: =DATE(Range!$N3,Range!$M3,Range!$L3) -> 36897 | P3: =TODAY() -> 46071 | Q3: =DATEDIF(Range!$O3,Range!$P3,"Y") -> 25 | R3: 7175 | S3: =Range!$R3*0.1 -> 717.5 | T3: =Range!$R3*0.03 -> 215.25 | U3: =Range!$R3-Range!$S3+Range!$T3 -> 6672.75 | V3: =IF(Range!$U3>=6000,"Over","Normal") -> Over | W3: =VLOOKUP(Range!$U3,$Z$10:$AA$14,2) -> 0.02 | Z3: Total Net | AA3: =SUM(Range!$U$2:$U$301) -> 1242807.4
A4: 1003 | B4: Ailya | C4: ShaRaf | D4: =PROPER(TRIM(Range!$C4&" "&Range!$C4)) -> Sharaf Sharaf | E4: Female | F4: 012 4071-7821 | G4: Saudi Arabia | H4: Half-Time | I4: Manufacturing | J4: Debt Card | K4: a.sharaf@email.com | L4: 7 | M4: 1 | N4: 2007 | O4: =DATE(Range!$N4,Range!$M4,Range!$L4) -> 39089 | P4: =TODAY() -> 46071 | Q4: =DATEDIF(Range!$O4,Range!$P4,"Y") -> 19 | R4: 4070 | S4: =Range!$R4*0.1 -> 407 | T4: =Range!$R4*0.03 -> 122.1 | U4: =Range!$R4-Range!$S4+Range!$T4 -> 3785.1 | V4: =IF(Range!$U4>=6000,"Over","Normal") -> Normal | W4: =VLOOKUP(Range!$U4,$Z$10:$AA$14,2) -> 0.05 | Z4: Average Net | AA4: =AVERAGE(U:U) -> 4142.6912
A5: 1004 | B5: Lwiy | C5: Qbany | D5: =PROPER(TRIM(Range!$C5&" "&Range!$C5)) -> Qbany Qbany | E5: Male | F5: 010 5618-2492 | G5: Sudan | H5: Full Time | I5: Account Management | J5: Hawala | K5: l.qbany@email.com | L5: 21 | M5: 1 | N5: 1993 | O5: =DATE(Range!$N5,Range!$M5,Range!$L5) -> 33990 | P5: =TODAY() -> 46071 | Q5: =DATEDIF(Range!$O5,Range!$P5,"Y") -> 33 | R5: 1906 | S5: =Range!$R5*0.1 -> 190.6 | T5: =Range!$R5*0.03 -> 57.18 | U5: =Range!$R5-Range!$S5+Range!$T5 -> 1772.58 | V5: =IF(Range!$U5>=6000,"Over","Normal") -> Normal | W5: =VLOOKUP(Range!$U5,$Z$10:$AA$14,2) -> 0.08 | Z5: Count of Emp. | AA5: =COUNT(A:A) -> 300
A6: 1005 | B6: Ahmad | C6: bikri | D6: =PROPER(TRIM(Range!$C6&" "&Range!$C6)) -> Bikri Bikri | E6: Male | F6: 011 7329-6122 | G6: Egypt | H6: Half-Time | I6: Account Management | J6: Hawala | K6: a.bikri@email.com | L6: 26 | M6: 1 | N6: 2019 | O6: =DATE(Range!$N6,Range!$M6,Range!$L6) -> 43491 | P6: =TODAY() -> 46071 | Q6: =DATEDIF(Range!$O6,Range!$P6,"Y") -> 7 | R6: 2600 | S6: =Range!$R6*0.1 -> 260 | T6: =Range!$R6*0.03 -> 78 | U6: =Range!$R6-Range!$S6+Range!$T6 -> 2418 | V6: =IF(Range!$U6>=6000,"Over","Normal") -> Normal | W6: =VLOOKUP(Range!$U6,$Z$10:$AA$14,2) -> 0.08 | Z6: Max Salary | AA6: =MAX(R:R) -> 7478
A7: 1006 | B7: Muhamad | C7: Zueitr | D7: =PROPER(TRIM(Range!$C7&" "&Range!$C7)) -> Zueitr Zueitr | E7: Male | F7: 011 2527-4512 | G7: Saudi Arabia | H7: Contract | I7: Quality Control | J7: Hawala | K7: m.zueitr@email.com | L7: 26 | M7: 1 | N7: 2003 | O7: =DATE(Range!$N7,Range!$M7,Range!$L7) -> 37647 | P7: =TODAY() -> 46071 | Q7: =DATEDIF(Range!$O7,Range!$P7,"Y") -> 23 | R7: 3753 | S7: =Range!$R7*0.1 -> 375.3 | T7: =Range!$R7*0.03 -> 112.59 | U7: =Range!$R7-Range!$S7+Range!$T7 -> 3490.29 | V7: =IF(Range!$U7>=6000,"Over","Normal") -> Normal | W7: =VLOOKUP(Range!$U7,$Z$10:$AA$14,2) -> 0.05 | Z7: Min Salary | AA7: =MIN(R:R) -> 742
A8: 1007 | B8: Iin | C8: Alhalaliu | D8: =PROPER(TRIM(Range!$C8&" "&Range!$C8)) -> Alhalaliu Alhalaliu | E8: Female | F8: 012 2640-9521 | G8: Iraq | H8: Full Time | I8: Engineering | J8: Master Card | K8: i.alhalaliu@email.com | L8: 29 | M8: 1 | N8: 1994 | O8: =DATE(Range!$N8,Range!$M8,Range!$L8) -> 34363 | P8: =TODAY() -> 46071 | Q8: =DATEDIF(Range!$O8,Range!$P8,"Y") -> 32 | R8: 5086 | S8: =Range!$R8*0.1 -> 508.6 | T8: =Range!$R8*0.03 -> 152.58 | U8: =Range!$R8-Range!$S8+Range!$T8 -> 4729.98 | V8: =IF(Range!$U8>=6000,"Over","Normal") -> Normal | W8: =VLOOKUP(Range!$U8,$Z$10:$AA$14,2) -> 0.05
A9: 1008 | B9: Muhamad | C9: Alaya | D9: =PROPER(TRIM(Range!$C9&" "&Range!$C9)) -> Alaya Alaya | E9: Male | F9: 010 8241-1311 | G9: Saudi Arabia | H9: Hourly | I9: Manufacturing | J9: Western Union | K9: m.alaya@email.com | L9: 29 | M9: 1 | N9: 2012 | O9: =DATE(Range!$N9,Range!$M9,Range!$L9) -> 40937 | P9: =TODAY() -> 46071 | Q9: =DATEDIF(Range!$O9,Range!$P9,"Y") -> 14 | R9: 2431 | S9: =Range!$R9*0.1 -> 243.1 | T9: =Range!$R9*0.03 -> 72.93 | U9: =Range!$R9-Range!$S9+Range!$T9 -> 2260.83 | V9: =IF(Range!$U9>=6000,"Over","Normal") -> Normal | W9: =VLOOKUP(Range!$U9,$Z$10:$AA$14,2) -> 0.08
A10: 1009 | B10: Susin | C10: Almilat | D10: =PROPER(TRIM(Range!$C10&" "&Range!$C10)) -> Almilat Almilat | E10: Female | F10: 012 1039-8810 | G10: Egypt | H10: Full Time | I10: Manufacturing | J10: Hawala | K10: s.almilat@email.com | L10: 30 | M10: 1 | N10: 2004 | O10: =DATE(Range!$N10,Range!$M10,Range!$L10) -> 38016 | P10: =TODAY() -> 46071 | Q10: =DATEDIF(Range!$O10,Range!$P10,"Y") -> 22 | R10: 2955 | S10: =Range!$R10*0.1 -> 295.5 | T10: =Range!$R10*0.03 -> 88.65 | U10: =Range!$R10-Range!$S10+Range!$T10 -> 2748.15 | V10: =IF(Range!$U10>=6000,"Over","Normal") -> Normal | W10: =VLOOKUP(Range!$U10,$Z$10:$AA$14,2) -> 0.08 | Z10: Salary | AA10: Extra Bonus %
A11: 1010 | B11: Muhamad | C11: Alrifaei | D11: =PROPER(TRIM(Range!$C11&" "&Range!$C11)) -> Alrifaei Alrifaei | E11: Male | F11: 010 7467-7662 | G11: Egypt | H11: Half-Time | I11: Engineering | J11: Hawala | K11: m.alrifaei@email.com | L11: 11 | M11: 2 | N11: 2003 | O11: =DATE(Range!$N11,Range!$M11,Range!$L11) -> 37663 | P11: =TODAY() -> 46071 | Q11: =DATEDIF(Range!$O11,Range!$P11,"Y") -> 23 | R11: 1948 | S11: =Range!$R11*0.1 -> 194.8 | T11: =Range!$R11*0.03 -> 58.44 | U11: =Range!$R11-Range!$S11+Range!$T11 -> 1811.64 | V11: =IF(Range!$U11>=6000,"Over","Normal") -> Normal | W11: =VLOOKUP(Range!$U11,$Z$10:$AA$14,2) -> 0.08 | Z11: 1 | AA11: 0.1
A12: 1011 | B12: Muhamad | C12: Alqadah | D12: =PROPER(TRIM(Range!$C12&" "&Range!$C12)) -> Alqadah Alqadah | E12: Male | F12: 011 8317-7634 | G12: Iraq | H12: Half-Time | I12: Marketing | J12: Western Union | K12: m.alqadah@email.com | L12: 11 | M12: 2 | N12: 1993 | O12: =DATE(Range!$N12,Range!$M12,Range!$L12) -> 34011 | P12: =TODAY() -> 46071 | Q12: =DATEDIF(Range!$O12,Range!$P12,"Y") -> 33 | R12: 3294 | S12: =Range!$R12*0.1 -> 329.4 | T12: =Range!$R12*0.03 -> 98.82 | U12: =Range!$R12-Range!$S12+Range!$T12 -> 3063.42 | V12: =IF(Range!$U12>=6000,"Over","Normal") -> Normal | W12: =VLOOKUP(Range!$U12,$Z$10:$AA$14,2) -> 0.05 | Z12: 1000 | AA12: 0.08
A13: 1012 | B13: Muhamad | C13: Iad | D13: =PROPER(TRIM(Range!$C13&" "&Range!$C13)) -> Iad Iad | E13: Male | F13: 011 6548-2919 | G13: Sudan | H13: Contract | I13: Engineering | J13: Debt Card | K13: m.iad@email.com | L13: 17 | M13: 2 | N13: 2005 | O13: =DATE(Range!$N13,Range!$M13,Range!$L13) -> 38400 | P13: =TODAY() -> 46071 | Q13: =DATEDIF(Range!$O13,Range!$P13,"Y") -> 21 | R13: 7123 | S13: =Range!$R13*0.1 -> 712.3 | T13: =Range!$R13*0.03 -> 213.69 | U13: =Range!$R13-Range!$S13+Range!$T13 -> 6624.39 | V13: =IF(Range!$U13>=6000,"Over","Normal") -> Over | W13: =VLOOKUP(Range!$U13,$Z$10:$AA$14,2) -> 0.02 | Z13: 3000 | AA13: 0.05
A14: 1013 | B14: Razaan | C14: Nasif | D14: =PROPER(TRIM(Range!$C14&" "&Range!$C14)) -> Nasif Nasif | E14: Female | F14: 010 6241-6559 | G14: Saudi Arabia | H14: Full Time | I14: Marketing | J14: Debt Card | K14: r.nasif@email.com | L14: 25 | M14: 2 | N14: 2019 | O14: =DATE(Range!$N14,Range!$M14,Range!$L14) -> 43521 | P14: =TODAY() -> 46071 | Q14: =DATEDIF(Range!$O14,Range!$P14,"Y") -> 6 | R14: 7236 | S14: =Range!$R14*0.1 -> 723.6 | T14: =Range!$R14*0.03 -> 217.08 | U14: =Range!$R14-Range!$S14+Range!$T14 -> 6729.48 | V14: =IF(Range!$U14>=6000,"Over","Normal") -> Over | W14: =VLOOKUP(Range!$U14,$Z$10:$AA$14,2) -> 0.02 | Z14: 6000 | AA14: 0.02
A15: 1014 | B15: Iilian | C15: mohamed | D15: =PROPER(TRIM(Range!$C15&" "&Range!$C15)) -> Mohamed Mohamed | E15: Female | F15: 012 0080-0351 | G15: Sudan | H15: Full Time | I15: Engineering | J15: Hawala | K15: i.dbs@email.com | L15: 26 | M15: 2 | N15: 2004 | O15: =DATE(Range!$N15,Range!$M15,Range!$L15) -> 38043 | P15: =TODAY() -> 46071 | Q15: =DATEDIF(Range!$O15,Range!$P15,"Y") -> 21 | R15: 6843 | S15: =Range!$R15*0.1 -> 684.3 | T15: =Range!$R15*0.03 -> 205.29 | U15: =Range!$R15-Range!$S15+Range!$T15 -> 6363.99 | V15: =IF(Range!$U15>=6000,"Over","Normal") -> Over | W15: =VLOOKUP(Range!$U15,$Z$10:$AA$14,2) -> 0.02
A16: 1015 | B16: Bayan | C16: mostafa | D16: =PROPER(TRIM(Range!$C16&" "&Range!$C16)) -> Mostafa Mostafa | E16: Female | F16: 011 5953-5296 | G16: Sudan | H16: Hourly | I16: Engineering | J16: Hawala | K16: b.qdw@email.com | L16: 2 | M16: 3 | N16: 2011 | O16: =DATE(Range!$N16,Range!$M16,Range!$L16) -> 40604 | P16: =TODAY() -> 46071 | Q16: =DATEDIF(Range!$O16,Range!$P16,"Y") -> 14 | R16: 1070 | S16: =Range!$R16*0.1 -> 107 | T16: =Range!$R16*0.03 -> 32.1 | U16: =Range!$R16-Range!$S16+Range!$T16 -> 995.1 | V16: =IF(Range!$U16>=6000,"Over","Normal") -> Normal | W16: =VLOOKUP(Range!$U16,$Z$10:$AA$14,2) -> 0.1
A17: 1016 | B17: Alaa | C17: Muhamad | D17: =PROPER(TRIM(Range!$C17&" "&Range!$C17)) -> Muhamad Muhamad | E17: Male | F17: 010 5319-7669 | G17: Saudi Arabia | H17: Hourly | I17: Engineering | J17: Debt Card | K17: a.muhamad@email.com | L17: 10 | M17: 3 | N17: 2020 | O17: =DATE(Range!$N17,Range!$M17,Range!$L17) -> 43900 | P17: =TODAY() -> 46071 | Q17: =DATEDIF(Range!$O17,Range!$P17,"Y") -> 5 | R17: 1493 | S17: =Range!$R17*0.1 -> 149.3 | T17: =Range!$R17*0.03 -> 44.79 | U17: =Range!$R17-Range!$S17+Range!$T17 -> 1388.49 | V17: =IF(Range!$U17>=6000,"Over","Normal") -> Normal | W17: =VLOOKUP(Range!$U17,$Z$10:$AA$14,2) -> 0.08
A18: 1017 | B18: Sandra | C18: Ziad | D18: =PROPER(TRIM(Range!$C18&" "&Range!$C18)) -> Ziad Ziad | E18: Female | F18: 011 2332-0982 | G18: Iraq | H18: Full Time | I18: Marketing | J18: Hawala | K18: s.ziad@email.com | L18: 6 | M18: 4 | N18: 1999 | O18: =DATE(Range!$N18,Range!$M18,Range!$L18) -> 36256 | P18: =TODAY() -> 46071 | Q18: =DATEDIF(Range!$O18,Range!$P18,"Y") -> 26 | R18: 5857 | S18: =Range!$R18*0.1 -> 585.7 | T18: =Range!$R18*0.03 -> 175.71 | U18: =Range!$R18-Range!$S18+Range!$T18 -> 5447.01 | V18: =IF(Range!$U18>=6000,"Over","Normal") -> Normal | W18: =VLOOKUP(Range!$U18,$Z$10:$AA$14,2) -> 0.05
A19: 1018 | B19: Farahad | C19: Husayn | D19: =PROPER(TRIM(Range!$C19&" "&Range!$C19)) -> Husayn Husayn | E19: Male | F19: 010 1442-5932 | G19: Iraq | H19: Contract | I19: IT | J19: Hawala | K19: f.husayn@email.com | L19: 12 | M19: 4 | N19: 2004 | O19: =DATE(Range!$N19,Range!$M19,Range!$L19) -> 38089 | P19: =TODAY() -> 46071 | Q19: =DATEDIF(Range!$O19,Range!$P19,"Y") -> 21 | R19: 5278 | S19: =Range!$R19*0.1 -> 527.8 | T19: =Range!$R19*0.03 -> 158.34 | U19: =Range!$R19-Range!$S19+Range!$T19 -> 4908.54 | V19: =IF(Range!$U19>=6000,"Over","Normal") -> Normal | W19: =VLOOKUP(Range!$U19,$Z$10:$AA$14,2) -> 0.05
A20: 1019 | B20: Ahed | C20: Salim | D20: =PROPER(TRIM(Range!$C20&" "&Range!$C20)) -> Salim Salim | E20: Female | F20: 011 6732-2351 | G20: Sudan | H20: Full Time | I20: IT | J20: Hawala | K20: a.salim@email.com | L20: 13 | M20: 4 | N20: 1999 | O20: =DATE(Range!$N20,Range!$M20,Range!$L20) -> 36263 | P20: =TODAY() -> 46071 | Q20: =DATEDIF(Range!$O20,Range!$P20,"Y") -> 26 | R20: 5710 | S20: =Range!$R20*0.1 -> 571 | T20: =Range!$R20*0.03 -> 171.3 | U20: =Range!$R20-Range!$S20+Range!$T20 -> 5310.3 | V20: =IF(Range!$U20>=6000,"Over","Normal") -> Normal | W20: =VLOOKUP(Range!$U20,$Z$10:$AA$14,2) -> 0.05
A21: 1020 | B21: Ayham | C21: Tutwnji | D21: =PROPER(TRIM(Range!$C21&" "&Range!$C21)) -> Tutwnji Tutwnji | E21: Male | F21: 011 8295-8045 | G21: Saudi Arabia | H21: Full Time | I21: Account Management | J21: Hawala | K21: a.tutwnji@email.com | L21: 28 | M21: 4 | N21: 2020 | O21: =DATE(Range!$N21,Range!$M21,Range!$L21) -> 43949 | P21: =TODAY() -> 46071 | Q21: =DATEDIF(Range!$O21,Range!$P21,"Y") -> 5 | R21: 6145 | S21: =Range!$R21*0.1 -> 614.5 | T21: =Range!$R21*0.03 -> 184.35 | U21: =Range!$R21-Range!$S21+Range!$T21 -> 5714.85 | V21: =IF(Range!$U21>=6000,"Over","Normal") -> Normal | W21: =VLOOKUP(Range!$U21,$Z$10:$AA$14,2) -> 0.05
A22: 1021 | B22: Samir | C22: Alsafdi | D22: =PROPER(TRIM(Range!$C22&" "&Range!$C22)) -> Alsafdi Alsafdi | E22: Male | F22: 010 8655-8298 | G22: Egypt | H22: Contract | I22: IT | J22: Western Union | K22: s.alsafdi@email.com | L22: 1 | M22: 5 | N22: 2012 | O22: =DATE(Range!$N22,Range!$M22,Range!$L22) -> 41030 | P22: =TODAY() -> 46071 | Q22: =DATEDIF(Range!$O22,Range!$P22,"Y") -> 13 | R22: 5278 | S22: =Range!$R22*0.1 -> 527.8 | T22: =Range!$R22*0.03 -> 158.34 | U22: =Range!$R22-Range!$S22+Range!$T22 -> 4908.54 | V22: =IF(Range!$U22>=6000,"Over","Normal") -> Normal | W22: =VLOOKUP(Range!$U22,$Z$10:$AA$14,2) -> 0.05
A23: 1022 | B23: Bilal | C23: Jalal | D23: =PROPER(TRIM(Range!$C23&" "&Range!$C23)) -> Jalal Jalal | E23: Male | F23: 010 2145-8500 | G23: Egypt | H23: Contract | I23: Manufacturing | J23: Debt Card | K23: b.jalal@email.com | L23: 7 | M23: 5 | N23: 1996 | O23: =DATE(Range!$N23,Range!$M23,Range!$L23) -> 35192 | P23: =TODAY() -> 46071 | Q23: =DATEDIF(Range!$O23,Range!$P23,"Y") -> 29 | R23: 6409 | S23: =Range!$R23*0.1 -> 640.9 | T23: =Range!$R23*0.03 -> 192.27 | U23: =Range!$R23-Range!$S23+Range!$T23 -> 5960.37 | V23: =IF(Range!$U23>=6000,"Over","Normal") -> Normal | W23: =VLOOKUP(Range!$U23,$Z$10:$AA$14,2) -> 0.05
A24: 1023 | B24: Riad | C24: Sahalul | D24: =PROPER(TRIM(Range!$C24&" "&Range!$C24)) -> Sahalul Sahalul | E24: Male | F24: 010 3436-0371 | G24: Saudi Arabia | H24: Full Time | I24: Manufacturing | J24: Hawala | K24: r.sahalul@email.com | L24: 12 | M24: 5 | N24: 2007 | O24: =DATE(Range!$N24,Range!$M24,Range!$L24) -> 39214 | P24: =TODAY() -> 46071 | Q24: =DATEDIF(Range!$O24,Range!$P24,"Y") -> 18 | R24: 7478 | S24: =Range!$R24*0.1 -> 747.8 | T24: =Range!$R24*0.03 -> 224.34 | U24: =Range!$R24-Range!$S24+Range!$T24 -> 6954.54 | V24: =IF(Range!$U24>=6000,"Over","Normal") -> Over | W24: =VLOOKUP(Range!$U24,$Z$10:$AA$14,2) -> 0.02
A25: 1024 | B25: Ahmad | C25: Ahmad | D25: =PROPER(TRIM(Range!$C25&" "&Range!$C25)) -> Ahmad Ahmad | E25: Male | F25: 011 2766-3217 | G25: Sudan | H25: Full Time | I25: Manufacturing | J25: Master Card | K25: a.ahmad@email.com | L25: 18 | M25: 5 | N25: 2002 | O25: =DATE(Range!$N25,Range!$M25,Range!$L25) -> 37394 | P25: =TODAY() -> 46071 | Q25: =DATEDIF(Range!$O25,Range!$P25,"Y") -> 23 | R25: 4621 | S25: =Range!$R25*0.1 -> 462.1 | T25: =Range!$R25*0.03 -> 138.63 | U25: =Range!$R25-Range!$S25+Range!$T25 -> 4297.53 | V25: =IF(Range!$U25>=6000,"Over","Normal") -> Normal | W25: =VLOOKUP(Range!$U25,$Z$10:$AA$14,2) -> 0.05
A26: 1025 | B26: Muhamad | C26: Altarah | D26: =PROPER(TRIM(Range!$C26&" "&Range!$C26)) -> Altarah Altarah | E26: Male | F26: 012 3389-6143 | G26: Egypt | H26: Contract | I26: Product Development | J26: Master Card | K26: m.altarah@email.com | L26: 19 | M26: 5 | N26: 2002 | O26: =DATE(Range!$N26,Range!$M26,Range!$L26) -> 37395 | P26: =TODAY() -> 46071 | Q26: =DATEDIF(Range!$O26,Range!$P26,"Y") -> 23 | R26: 2093 | S26: =Range!$R26*0.1 -> 209.3 | T26: =Range!$R26*0.03 -> 62.79 | U26: =Range!$R26-Range!$S26+Range!$T26 -> 1946.49 | V26: =IF(Range!$U26>=6000,"Over","Normal") -> Normal | W26: =VLOOKUP(Range!$U26,$Z$10:$AA$14,2) -> 0.08
... A301: 1300 | B301: Ahmad | C301: Qadimati | D301: =PROPER(TRIM(Range!$C301&" "&Range!$C301)) -> Qadimati Qadimati | E301: Male | F301: 011 5056-6641 | G301: Iraq | H301: Full Time | I301: Marketing | J301: Western Union | K301: a.qadimati@email.com | L301: 8 | M301: 3 | N301: 2015 | O301: =DATE(Range!$N301,Range!$M301,Range!$L301) -> 42071 | P301: =TODAY() -> 46071 | Q301: =DATEDIF(Range!$O301,Range!$P301,"Y") -> 10 | R301: 3294 | S301: =Range!$R301*0.1 -> 329.4 | T301: =Range!$R301*0.03 -> 98.82 | U301: =Range!$R301-Range!$S301+Range!$T301 -> 3063.42 | V301: =IF(Range!$U301>=6000,"Over","Normal") -> Normal | W301: =VLOOKUP(Range!$U301,$Z$10:$AA$14,2) -> 0.05

Sheet Report 2
J2: Total Salaries | K2: =GETPIVOTDATA("Sum of Net Salary",Pivot!$A$3) -> 1242807.4 | L2: Count of Employees | N2: =GETPIVOTDATA("Count of ID",Pivot!$A$3) -> 300 | P2: Average of Experience Years | S2: =GETPIVOTDATA("Average of Experience Year",Pivot!$A$3) -> 19.146667
A5: Hr Annual Dashboard
